fails_components_jupyter_launcher/__init__.py
fails_components_jupyter_launcher/labextension/_version.py
fails_components_jupyter_launcher/labextension/package.json
fails_components_jupyter_launcher/labextension/schemas/@fails-components/jupyter-launcher/package.json.orig
fails_components_jupyter_launcher/labextension/static/0.371eab911b7f59d86872.js
fails_components_jupyter_launcher/labextension/static/488.97dfaaa2348978c14bb7.js
fails_components_jupyter_launcher/labextension/static/961.5559e707b06977387e04.js
fails_components_jupyter_launcher/labextension/static/remoteEntry.6a31ac66a064fe9893b6.js
fails_components_jupyter_launcher/labextension/static/style.js
fails_components_jupyter_launcher/labextension/static/third-party-licenses.json
fails_components_jupyter_launcher-0.0.5.data/data/share/jupyter/labextensions/@fails-components/jupyter-launcher/_version.py
fails_components_jupyter_launcher-0.0.5.data/data/share/jupyter/labextensions/@fails-components/jupyter-launcher/package.json
fails_components_jupyter_launcher-0.0.5.data/data/share/jupyter/labextensions/@fails-components/jupyter-launcher/schemas/@fails-components/jupyter-launcher/package.json.orig
fails_components_jupyter_launcher-0.0.5.data/data/share/jupyter/labextensions/@fails-components/jupyter-launcher/static/0.371eab911b7f59d86872.js
fails_components_jupyter_launcher-0.0.5.data/data/share/jupyter/labextensions/@fails-components/jupyter-launcher/static/488.97dfaaa2348978c14bb7.js
fails_components_jupyter_launcher-0.0.5.data/data/share/jupyter/labextensions/@fails-components/jupyter-launcher/static/961.5559e707b06977387e04.js
fails_components_jupyter_launcher-0.0.5.data/data/share/jupyter/labextensions/@fails-components/jupyter-launcher/static/remoteEntry.6a31ac66a064fe9893b6.js
fails_components_jupyter_launcher-0.0.5.data/data/share/jupyter/labextensions/@fails-components/jupyter-launcher/static/style.js
fails_components_jupyter_launcher-0.0.5.dist-info/METADATA
fails_components_jupyter_launcher-0.0.5.dist-info/WHEEL
fails_components_jupyter_launcher-0.0.5.dist-info/licenses/LICENSE
fails_components_jupyter_launcher-0.0.5.dist-info/RECORD
